fetchman/__init__.py
fetchman/downloader/__init__.py
fetchman/downloader/base_downloder.py
fetchman/downloader/requests_downloader.py
fetchman/downloader/selenium_downloader.py
fetchman/downloader/web_driver_pool.py
fetchman/downloader/http/__init__.py
fetchman/downloader/http/selenium_response.py
fetchman/downloader/http/spider_request.py
fetchman/downloader/http/spider_response.py
fetchman/downloader/proxy/__init__.py
fetchman/downloader/proxy/proxy_pool.py
fetchman/loginer/__init__.py
fetchman/loginer/base_loginer.py
fetchman/pipeline/__init__.py
fetchman/pipeline/base_pipeline.py
fetchman/pipeline/console_pipeline.py
fetchman/pipeline/pic_pipeline.py
fetchman/pipeline/pipe_item.py
fetchman/pipeline/test_pipeline.py
fetchman/processor/__init__.py
fetchman/processor/base_processor.py
fetchman/processor/test_processor.py
fetchman/scheduler/__init__.py
fetchman/scheduler/bloom_filter.py
fetchman/scheduler/queue.py
fetchman/settings/__init__.py
fetchman/settings/default_settings.py
fetchman/spider/__init__.py
fetchman/spider/spider_core.py
fetchman/utils/__init__.py
fetchman/utils/cookie.py
fetchman/utils/decorator.py
fetchman/utils/httpobj.py
fetchman/utils/python.py
fetchman/utils/reqser.py
fetchman-0.4.6.dist-info/METADATA
fetchman-0.4.6.dist-info/RECORD
fetchman-0.4.6.dist-info/WHEEL
fetchman-0.4.6.dist-info/top_level.txt
news-crawler/__init__.py
news-crawler/gzb.py
news-crawler/tuliu.py
news-crawler/zhue.py
news-crawler/pipelines/__init__.py
news-crawler/pipelines/console_pipeline.py
news-crawler/pipelines/database_pipeline.py
news-crawler/pipelines/fa_news.py
news-crawler/pipelines/pic_pipeline.py
news-crawler/util/__init__.py
news-crawler/util/seq_util.py
