Metadata-Version: 2.1
Name: fetchman
Version: 0.4.6
Summary: a simple spider system
Home-page: https://github.com/DarkSand/fetchman
Author: DaVinciDW
Author-email: darkwings_love@163.com
Maintainer: DaVinciDW
Maintainer-email: darkwings_love@163.com
License: Apache License, Version 2.0
Platform: all
Classifier: Development Status :: 2 - Pre-Alpha
Classifier: Environment :: Web Environment
Classifier: Intended Audience :: Developers
Classifier: Operating System :: OS Independent
Classifier: Topic :: Text Processing :: Indexing
Classifier: Topic :: Utilities
Classifier: Topic :: Internet
Classifier: Topic :: Software Development :: Libraries :: Python Modules
Classifier: Programming Language :: Python :: 2.7
Classifier: Programming Language :: Python :: 3.4
Provides-Extra: test
Provides-Extra: all
Requires-Dist: redis (>=2.10.5)
Requires-Dist: requests (>=2.13.0)
Requires-Dist: six (>=1.10.0)
Requires-Dist: grequests (>=0.3.0)
Requires-Dist: selenium (>=2.53.6)
Requires-Dist: lxml (>=3.7.2)
Requires-Dist: beautifulsoup4 (>=4.6.0)
Provides-Extra: all
Requires-Dist: redis (>=2.10.5); extra == 'all'
Requires-Dist: requests (>=2.13.0); extra == 'all'
Requires-Dist: six (>=1.10.0); extra == 'all'
Requires-Dist: grequests (>=0.3.0); extra == 'all'
Requires-Dist: selenium (>=2.53.6); extra == 'all'
Requires-Dist: lxml (>=3.7.2); extra == 'all'
Requires-Dist: beautifulsoup4 (>=4.6.0); extra == 'all'
Provides-Extra: test
Requires-Dist: unittest2 (>=0.5.1); extra == 'test'
Requires-Dist: coverage; extra == 'test'
